combomethod.py
combomethod-1.0.12.dist-info/DESCRIPTION.rst
combomethod-1.0.12.dist-info/METADATA
combomethod-1.0.12.dist-info/RECORD
combomethod-1.0.12.dist-info/WHEEL
combomethod-1.0.12.dist-info/metadata.json
combomethod-1.0.12.dist-info/top_level.txt
